flopsearch-0.1.3.dist-info/METADATA
flopsearch-0.1.3.dist-info/WHEEL
flopsearch.libs/libgcc_s-39080030.so.1
flopsearch/__init__.py
flopsearch/__init__.pyi
flopsearch/flopsearch.cpython-313t-aarch64-linux-musl.so
flopsearch/py.typed
flopsearch-0.1.3.dist-info/RECORD
