Metadata-Version: 2.4
Name: flopsearch
Version: 0.1.3
Classifier: Programming Language :: Rust
Classifier: Programming Language :: Python :: Implementation :: CPython
Classifier: Programming Language :: Python :: Implementation :: PyPy
Summary: Python package providing an implementation of the FLOP causal discovery algorithm for linear additive noise models
Keywords: causal discovery,DAGs,Bayesian networks,structure learning
Author: Sebastian Weichwald, Leonard Henckel
Author-email: Marcel Wienöbst <marcel.wienoebst@gmx.de>
Requires-Python: >=3.8
